cookiedough/__init__.py
cookiedough/__main__.py
cookiedough/config.patch
cookiedough/icons.py
cookiedough/rollout.py
cookiedough/scan.py
cookiedough/uidata.json
cookiedough/update.py
cookiedough/help/__init__.py
cookiedough/help/contribute.page
cookiedough/help/improve.page
cookiedough/help/index.page
cookiedough/help/menu.page
cookiedough/help/patch.md
cookiedough/help/patch.page
cookiedough/help/rollout.page
cookiedough/help/screenshot.jpeg
cookiedough/help/search.page
cookiedough/help/settings.page
cookiedough/help/uidata.page
cookiedough/help/usage.page
cookiedough-0.3.0.data/data/man/man1/cookiecutter.1
cookiedough-0.3.0.data/data/man/man1/cookiedough.1
cookiedough-0.3.0.dist-info/LICENSE
cookiedough-0.3.0.dist-info/METADATA
cookiedough-0.3.0.dist-info/WHEEL
cookiedough-0.3.0.dist-info/entry_points.txt
cookiedough-0.3.0.dist-info/top_level.txt
cookiedough-0.3.0.dist-info/RECORD
