Metadata-Version: 2.1
Name: cookiedough
Version: 0.3.0
Summary: browser and install GUI for cookiecutter templates
Home-page: https://fossil.include-once.org/cookiedough/
License: proprietary
Project-URL: Freshcode, https://freshcode.club/projects/cookiedough
Keywords: cookiecutter,browser,templates
Platform: UNKNOWN
Classifier: Development Status :: 4 - Beta
Classifier: Topic :: Internet :: WWW/HTTP :: Browsers
Classifier: Topic :: Multimedia :: Graphics :: Viewers
Classifier: Topic :: Software Development :: Code Generators
Classifier: Topic :: Software Development :: Libraries :: Python Modules
Requires-Python: >= 3.8
Requires-Dist: PySimpleGUI (>=4.37)
Requires-Dist: appdirs
Requires-Dist: cookiecutter (>=1.7)
Requires-Dist: pluginconf
Requires-Dist: requests
Provides-Extra: build
Requires-Dist: pluginconf ; extra == 'build'
Requires-Dist: setuptools ; extra == 'build'
Provides-Extra: unused
Requires-Dist: ttkthemes ; extra == 'unused'
